setup.py
pystachios/__init__.py
pystachios/geometry.py
pystachios/operations.py
pystachios/pystachios.py
pystachios/setup.py
pystachios.egg-info/PKG-INFO
pystachios.egg-info/SOURCES.txt
pystachios.egg-info/dependency_links.txt
pystachios.egg-info/top_level.txt