Metadata-Version: 2.1
Name: pystachios
Version: 0.1.4
Summary: Let's keep testing this thing called pypi
Author: Felipe Kautzmann
Author-email: <recuerdaesto@gmail.com>
Keywords: python,first package
Classifier: Development Status :: 3 - Alpha
Classifier: Intended Audience :: Education
Classifier: Programming Language :: Python :: 2
Classifier: Programming Language :: Python :: 3
Classifier: Operating System :: MacOS :: MacOS X
Classifier: Operating System :: Microsoft :: Windows
